fact_sphere_cli/__about__.py
fact_sphere_cli/__init__.py
fact_sphere_cli/__main__.py
fact_sphere_cli/cli.py
fact_sphere_cli-1.1.0.dist-info/entry_points.txt
fact_sphere_cli-1.1.0.dist-info/LICENSE
fact_sphere_cli-1.1.0.dist-info/WHEEL
fact_sphere_cli-1.1.0.dist-info/METADATA
fact_sphere_cli-1.1.0.dist-info/RECORD
